qtwasmserver/qtwasmserver.py
qtwasmserver/setup.py
qtwasmserver-0.1.5.dist-info/METADATA
qtwasmserver-0.1.5.dist-info/WHEEL
qtwasmserver-0.1.5.dist-info/entry_points.txt
qtwasmserver-0.1.5.dist-info/licenses/LICENSE
qtwasmserver-0.1.5.dist-info/RECORD
