Metadata-Version: 2.4
Name: qtwasmserver
Version: 0.1.5
Summary: Development Web Server for Qt for Webassembly
Project-URL: Homepage, https://github.com/msorvig/qtwasmserver
Project-URL: Bug Tracker, https://github.com/msorvig/qtwasmserver/issues
Author-email: Morten Sørvig <msorvig@gmail.com>
License-File: LICENSE
Classifier: License :: OSI Approved :: MIT License
Classifier: Operating System :: OS Independent
Classifier: Programming Language :: Python :: 3
Requires-Python: >=3.7
Requires-Dist: brotlipy>=0.7
Requires-Dist: httpcompressionserver>=0.5
Requires-Dist: netifaces>=0.10
